skype_downloader/__init__.py
skype_downloader/skype_main.py
bhaskar_kernel_easy_skype-0.0.3.dist-info/LICENSE
bhaskar_kernel_easy_skype-0.0.3.dist-info/METADATA
bhaskar_kernel_easy_skype-0.0.3.dist-info/WHEEL
bhaskar_kernel_easy_skype-0.0.3.dist-info/entry_points.txt
bhaskar_kernel_easy_skype-0.0.3.dist-info/top_level.txt
bhaskar_kernel_easy_skype-0.0.3.dist-info/RECORD
